proxyvars/__init__.py
proxyvars/py.typed
proxyvars-0.10.0.dist-info/LICENSE
proxyvars-0.10.0.dist-info/METADATA
proxyvars-0.10.0.dist-info/WHEEL
proxyvars-0.10.0.dist-info/RECORD
