Metadata-Version: 2.1
Name: proxyvars
Version: 0.10.0
Summary: Callback-based object proxies in Python.
Home-page: https://github.com/bswck/proxyvars
License: MIT
Author: bswck
Author-email: bartoszpiotrslawecki@gmail.com
Requires-Python: >=3.8
Classifier: License :: OSI Approved :: MIT License
Classifier: Programming Language :: Python :: 3
Classifier: Programming Language :: Python :: 3.8
Classifier: Programming Language :: Python :: 3.9
Classifier: Programming Language :: Python :: 3.10
Classifier: Programming Language :: Python :: 3.11
Classifier: Programming Language :: Python :: 3.12
Project-URL: Coverage, https://coverage-badge.samuelcolvin.workers.dev/redirect/bswck/proxyvars
Project-URL: Documentation, https://proxyvars.readthedocs.io/en/latest/
Project-URL: Distribution, https://pypi.org/project/proxyvars/
Project-URL: Issues, https://github.com/bswck/proxyvars/issues
